qtneat/__init__.py
qtneat/main.py
qtneat/style/__init__.py
qtneat/style/qtSassTheme.py
qtneat/style/ico/__init__.py
qtneat/style/ico/dark/__init__.py
qtneat/style/ico/light/__init__.py
qtneat/style/sass/__init__.py
qtneat/style/var/__init__.py
qtneat/style/var/dark/__init__.py
qtneat/style/var/dark/dark_blue/__init__.py
qtneat/style/var/dark/dark_gray/__init__.py
qtneat/style/var/light/__init__.py
qtneat/style/var/light/light_blue/__init__.py
qtneat/style/var/light/light_gray/__init__.py
qtneat/window/__init__.py
qtneat/window/baseWindow.py
qtneat/window/cornerWidget.py
qtneat/window/icons.py
qtneat/window/macCornerWidget.py
qtneat/window/menuBar.py
qtneat/window/titleBar.py
qtneat/window/toolBar.py
qtneat/window/window.py
qtneat/window/windowsCornerWidget.py
qtneat-0.0.7.dist-info/LICENSE
qtneat-0.0.7.dist-info/METADATA
qtneat-0.0.7.dist-info/WHEEL
qtneat-0.0.7.dist-info/top_level.txt
qtneat-0.0.7.dist-info/RECORD
