Metadata-Version: 2.1
Name: qtneat
Version: 0.0.7
Summary: Set the Qt frameless titlebar/theme easily
Home-page: https://github.com/yjg30737/qtneat.git
Author: Jung Gyu Yoon
Author-email: yjg30737@gmail.com
License: MIT
License-File: LICENSE
Requires-Dist: qtawesome (>=0.0.1)
Requires-Dist: pyqt-svg-button (>=0.0.1)
Requires-Dist: pyqt-svg-icon-text-widget (>=0.0.1)
